pyrat/__init__.py
pyrat/gui/cheese/cheese.png
pyrat/gui/cheese/cheese_eaten.png
pyrat/gui/cheese/cheese_half.png
pyrat/gui/cheese/cheese_missing.png
pyrat/gui/drawings/pyrat.png
pyrat/gui/drawings/pyrat_go.png
pyrat/gui/drawings/pyrat_preprocessing.png
pyrat/gui/endgame/first.png
pyrat/gui/endgame/game_over.wav
pyrat/gui/endgame/others.png
pyrat/gui/endgame/second.png
pyrat/gui/endgame/third.png
pyrat/gui/flag/flag.png
pyrat/gui/flag/flag_shadow.png
pyrat/gui/ground/tile1.png
pyrat/gui/ground/tile10.png
pyrat/gui/ground/tile2.png
pyrat/gui/ground/tile3.png
pyrat/gui/ground/tile4.png
pyrat/gui/ground/tile5.png
pyrat/gui/ground/tile6.png
pyrat/gui/ground/tile7.png
pyrat/gui/ground/tile8.png
pyrat/gui/ground/tile9.png
pyrat/gui/icon/pyrat.png
pyrat/gui/mud/mud.png
pyrat/gui/players/ghost/avatar.png
pyrat/gui/players/ghost/cheese_eaten.wav
pyrat/gui/players/ghost/east.png
pyrat/gui/players/ghost/neutral.png
pyrat/gui/players/ghost/north.png
pyrat/gui/players/ghost/south.png
pyrat/gui/players/ghost/west.png
pyrat/gui/players/mario/avatar.png
pyrat/gui/players/mario/cheese_eaten.wav
pyrat/gui/players/mario/east.png
pyrat/gui/players/mario/neutral.png
pyrat/gui/players/mario/north.png
pyrat/gui/players/mario/south.png
pyrat/gui/players/mario/west.png
pyrat/gui/players/python/avatar.png
pyrat/gui/players/python/cheese_eaten.wav
pyrat/gui/players/python/east.png
pyrat/gui/players/python/neutral.png
pyrat/gui/players/python/north.png
pyrat/gui/players/python/south.png
pyrat/gui/players/python/west.png
pyrat/gui/players/rat/avatar.png
pyrat/gui/players/rat/cheese_eaten.wav
pyrat/gui/players/rat/east.png
pyrat/gui/players/rat/neutral.png
pyrat/gui/players/rat/north.png
pyrat/gui/players/rat/south.png
pyrat/gui/players/rat/west.png
pyrat/gui/wall/corner.png
pyrat/gui/wall/wall.png
pyrat/src/BigHolesRandomMaze.py
pyrat/src/FixedPlayer.py
pyrat/src/Game.py
pyrat/src/GameState.py
pyrat/src/Graph.py
pyrat/src/HolesOnSideRandomMaze.py
pyrat/src/Maze.py
pyrat/src/MazeFromDict.py
pyrat_game-6.2.14.dist-info/licenses/LICENSE
pyrat_game-6.2.14.dist-info/METADATA
pyrat_game-6.2.14.dist-info/WHEEL
pyrat_game-6.2.14.dist-info/top_level.txt
pyrat_game-6.2.14.dist-info/RECORD
