Metadata-Version: 2.4
Name: pyrat-game
Version: 6.2.14
Summary: PyRat software used in the computer science course at IMT Atlantique
Author-email: Bastien Pasdeloup <bastien.pasdeloup@imt-atlantique.fr>
License-Expression: MIT
Project-URL: Homepage, https://github.com/BastienPasdeloup/PyRat
Project-URL: Documentation, https://bastienpasdeloup.github.io/PyRat
Project-URL: Issues, https://github.com/BastienPasdeloup/PyRat/issues
Project-URL: PyPI, https://pypi.org/project/pyrat-game
Project-URL: Course, https://hub.imt-atlantique.fr/ueinfo-fise1a
Classifier: Programming Language :: Python
License-File: LICENSE
Requires-Dist: pygame
Requires-Dist: colored
Requires-Dist: distinctipy
Requires-Dist: scipy
Requires-Dist: tqdm
Requires-Dist: matplotlib
Requires-Dist: pyfakefs
Provides-Extra: numpy
Requires-Dist: numpy; extra == "numpy"
Provides-Extra: torch
Requires-Dist: torch; extra == "torch"
Provides-Extra: docs
Requires-Dist: sphinx; extra == "docs"
Requires-Dist: sphinx-autodoc-typehints; extra == "docs"
Requires-Dist: furo; extra == "docs"
Dynamic: license-file
